table2md/__init__.py
table2md-1.1.0.dist-info/LICENSE
table2md-1.1.0.dist-info/METADATA
table2md-1.1.0.dist-info/WHEEL
table2md-1.1.0.dist-info/top_level.txt
table2md-1.1.0.dist-info/RECORD
