Metadata-Version: 2.1
Name: table2md
Version: 1.1.0
Summary: Print tabular data in markdown format
Home-page: https://github.com/MKuranowski/table2md
Author: Mikołaj Kuranowski
Author-email: mkuranowski+pypackages@gmail.com
License: MIT
Project-URL: Bug Tracker, https://github.com/MKuranowski/table2md/issues
Classifier: Programming Language :: Python :: 3
Classifier: License :: OSI Approved :: MIT License
Classifier: Operating System :: OS Independent
Requires-Python: >=3.6
License-File: LICENSE
Requires-Dist: typing-extensions ; python_version < "3.8"
